majormode/__init__.py
majormode/mercurius/__init__.py
majormode/mercurius/constant/__init__.py
majormode/mercurius/constant/place.py
majormode/mercurius/model/__init__.py
majormode/mercurius/model/address.py
majormode/mercurius/model/place.py
mercurius_core_library-1.0.8.dist-info/METADATA
mercurius_core_library-1.0.8.dist-info/WHEEL
mercurius_core_library-1.0.8.dist-info/top_level.txt
mercurius_core_library-1.0.8.dist-info/RECORD
