Metadata-Version: 2.1
Name: mercurius-core-library
Version: 1.0.8
Summary: Mercurius Core Python Library
Home-page: UNKNOWN
Author: Daniel CAUNE
Author-email: daniel.caune@gmail.com
License: MIT
Platform: any
Classifier: Development Status :: 5 - Production/Stable
Classifier: License :: OSI Approved :: MIT License
Classifier: Operating System :: OS Independent
Classifier: Programming Language :: Python
Classifier: Topic :: Software Development :: Libraries
Requires-Python: >=3
Requires-Dist: numpy
Requires-Dist: perseus-core-library
